pydub/__init__.py
pydub/_meter.py
pydub/_processor/__init__.py
pydub/_processor/command.py
pydub/_processor/enums.py
pydub/_processor/processor.py
pydub/audio_segment.py
pydub/effects.py
pydub/exceptions.py
pydub/generators.py
pydub/logging_utils.py
pydub/playback.py
pydub/pyaudioop.py
pydub/sample.c
pydub/sample.pyi
pydub/sample.pyx
pydub/scipy_effects.py
pydub/silence.py
pydub/utils.py
pozalabs_pydub-0.30.post1.dist-info/LICENSE
pozalabs_pydub-0.30.post1.dist-info/METADATA
pozalabs_pydub-0.30.post1.dist-info/WHEEL
pozalabs_pydub-0.30.post1.dist-info/RECORD
